MANIFEST.in
README.rst
setup.py
docs/HISTORY.txt
docs/images/screenshot1.png
openapp_indivo/__init__.py
openapp_indivo/adminsite/__init__.py
openapp_indivo/adminsite/admin.py
openapp_indivo/adminsite/models.py
openapp_indivo/adminsite/test_settings.py
openapp_indivo/adminsite/test_urls.py
openapp_indivo/adminsite/tests.py
openapp_indivo/adminsite/urls.py
openapp_indivo/adminsite/views.py
openapp_indivo/adminsite/templates/admin/index.html
openapp_indivo/adminsite/templates/admin/index_django14.html
openapp_indivo/adminsite/templates/admin/indivo/change_form.html
openapp_indivo/adminsite/templates/admin/indivo/change_form_record.html
openapp_indivo/adminsite/templates/openapp_indivo_adminsite/import_document.html
openapp_indivo_adminsite.egg-info/PKG-INFO
openapp_indivo_adminsite.egg-info/SOURCES.txt
openapp_indivo_adminsite.egg-info/dependency_links.txt
openapp_indivo_adminsite.egg-info/entry_points.txt
openapp_indivo_adminsite.egg-info/namespace_packages.txt
openapp_indivo_adminsite.egg-info/not-zip-safe
openapp_indivo_adminsite.egg-info/requires.txt
openapp_indivo_adminsite.egg-info/top_level.txt