Metadata-Version: 1.0
Name: openapp-indivo-adminsite
Version: 0.1
Summary: Admin Site for Indivo
Home-page: https://github.com/kevingill1966/openapp_indivo_adminsite
Author: Kevin Gill (www.OpenApp.ie)
Author-email: kevin.gill@openapp.ie
License: GPLv3
Keywords: indivo
Platform: UNKNOWN
Classifier: Development Status :: 3 - Alpha
Classifier: Intended Audience :: Healthcare Industry
Classifier: Framework :: Django
Classifier: License :: OSI Approved :: GNU General Public License v3 (GPLv3)
Classifier: Natural Language :: English
Classifier: Programming Language :: Python
Classifier: Topic :: Software Development :: Libraries :: Python Modules
Classifier: Operating System :: POSIX
Classifier: Topic :: Scientific/Engineering :: Medical Science Apps.
